PfsenseFauxapi/PfsenseFauxapi.py
PfsenseFauxapi/__init__.py
PfsenseFauxapi/__version__.py
pfsense_fauxapi-20200718.2.data/scripts/fauxapi
tests/__init__.py
tests/test_PfsenseFauxapi.py
pfsense_fauxapi-20200718.2.dist-info/LICENSE
pfsense_fauxapi-20200718.2.dist-info/METADATA
pfsense_fauxapi-20200718.2.dist-info/WHEEL
pfsense_fauxapi-20200718.2.dist-info/top_level.txt
pfsense_fauxapi-20200718.2.dist-info/RECORD
